pppiv/__init__.py
pppiv/main.py
pppiv-0.1.2.dist-info/entry_points.txt
pppiv-0.1.2.dist-info/LICENSE
pppiv-0.1.2.dist-info/WHEEL
pppiv-0.1.2.dist-info/METADATA
pppiv-0.1.2.dist-info/RECORD
