Metadata-Version: 2.1
Name: pppiv
Version: 0.1.2
Summary: Poetry Python Path Injector for VSCode
License: MIT
Author: Masahiro Wada
Author-email: argon.argon.argon@gmail.com
Requires-Python: >=3.6,<4.0
Classifier: License :: OSI Approved :: MIT License
Classifier: Programming Language :: Python :: 3
Classifier: Programming Language :: Python :: 3.6
Classifier: Programming Language :: Python :: 3.7
Classifier: Programming Language :: Python :: 3.8
Requires-Dist: black (>=19.10b0,<20.0)
Requires-Dist: click (>=7.0,<8.0)
Requires-Dist: poetry (>=1.0.0,<2.0.0)
